jsondetective/__init__.py
jsondetective/analyzer.py
jsondetective/cli.py
jsondetective/dataclass_gen.py
jsondetective-1.0.2.dist-info/LICENSE
jsondetective-1.0.2.dist-info/METADATA
jsondetective-1.0.2.dist-info/WHEEL
jsondetective-1.0.2.dist-info/entry_points.txt
jsondetective-1.0.2.dist-info/top_level.txt
jsondetective-1.0.2.dist-info/RECORD
