Metadata-Version: 2.1
Name: jsondetective
Version: 1.0.2
Summary: Instantly understand JSON structure through automatic schema inference
Home-page: https://github.com/timf34/jsondetective
Author: Tim Farrelly
Author-email: timf34@gmail.com
Classifier: Programming Language :: Python :: 3
Classifier: License :: OSI Approved :: MIT License
Classifier: Operating System :: OS Independent
Requires-Python: >=3.7
License-File: LICENSE
Requires-Dist: rich>=13.0.0
Requires-Dist: click>=7.1.2
